<page id="pre-124-e2-tec"><config><references>help-TEC</references></config><objects><object linkID="breadcrumb_title"><params><params_xml><titlePrefix>&lt;b&gt;Unit 124&lt;/b&gt;</titlePrefix><title>&lt;b&gt;In&lt;/b&gt;/&lt;b&gt;at&lt;/b&gt;/&lt;b&gt;on&lt;/b&gt; (position) 2</title></params_xml><custom_style_name /><sharedTokenBankId /><is_sequential>False</is_sequential><is_compulsory>False</is_compulsory><states><state id="queued" visible="True" enabled="False" /><state id="in_progress" visible="True" enabled="True" /><state id="complete" visible="True" enabled="True" /><state id="checked" visible="True" enabled="True" /><state id="closed" visible="True" enabled="False" /></states></params></object><object linkID="exercise"><params><custom_style_name /><is_sequential>false</is_sequential><is_compulsory>false</is_compulsory><is_marked>true</is_marked><show_marking_controls>true</show_marking_controls><states><state id="block_checked" visible="true" enabled="true" /><state id="block_closed" visible="true" enabled="true" /><state id="block_in_progress" visible="true" enabled="true" /><state id="block_queued" visible="true" enabled="false" /><state id="block_complete" visible="true" enabled="true" /></states><marking><scoreBand><threshold>50</threshold><feedback>You got [score]%. Correct.</feedback></scoreBand><scoreBand><threshold>0</threshold><feedback>You got [score]%. Incorrect.</feedback></scoreBand></marking><timer enabled="false" allowCheck="true"><level name="Level One"><seconds>60</seconds></level></timer><properties><property id="child_count">6</property></properties><params_xml><exerciseID /><at_heading>Exercise 2</at_heading><attemptsAllowed>-1</attemptsAllowed><minExerciseHeight>0</minExerciseHeight><modelAnswersEnabled>true</modelAnswersEnabled><feedbackEnabled>true</feedbackEnabled><feedbackPopUpEnabled>false</feedbackPopUpEnabled></params_xml></params></object><object linkID="rubric"><params><instruction_str>&lt;p&gt;Are the underlined prepositions right or wrong? Correct them where necessary. &lt;/p&gt;</instruction_str><instruction_audio_url /><instruction_label>English</instruction_label><alt_instructions /><custom_style_name /><sharedTokenBankId /><is_sequential>False</is_sequential><is_compulsory>False</is_compulsory><states><state id="queued" visible="True" enabled="False" /><state id="in_progress" visible="True" enabled="True" /><state id="complete" visible="True" enabled="True" /><state id="checked" visible="True" enabled="True" /><state id="closed" visible="True" enabled="False" /></states></params></object><object linkID="spacer"><params><params_xml><useHeight>true</useHeight><height>260</height></params_xml><alignment>left</alignment><alignPercent>70</alignPercent></params></object><object linkID="image_viewer"><params><isAnimation>false</isAnimation><showIcon>none</showIcon><url_str>learning_objects/assets/extra_art_u124_ex2__bkfc57.jpg</url_str><showBorder>true</showBorder><title_str /><description_str /><alt_text_str /><instruct_str /><instruct_panel_str>If you are unsure about how the animation above works click the "Instructions" button for help</instruct_panel_str><instruct_btn_str>INSTRUCTIONS</instruct_btn_str><alignment>right</alignment><alignPercent>30</alignPercent><custom_style_name /><sharedTokenBankId /><is_sequential>False</is_sequential><is_compulsory>False</is_compulsory><states><state id="queued" visible="True" enabled="False" /><state id="in_progress" visible="True" enabled="True" /><state id="complete" visible="True" enabled="True" /><state id="checked" visible="True" enabled="True" /><state id="closed" visible="True" enabled="False" /></states></params></object><object linkID="text_edit_correction"><params><params_xml><mcq_xml isMarked="false" isActivity="true"><at_heading>Text Edit Correction</at_heading><instruction_str /><attemptsFailFeedback_str>The interaction will now be completed for you.</attemptsFailFeedback_str><attemptsRemain_xml>&lt;text&gt;You have &lt;/text&gt;&lt;val id="attempts"/&gt;&lt;choose id="attempts"&gt;&lt;sgl&gt; attempt&lt;/sgl&gt;&lt;pl&gt; attempts&lt;/pl&gt;&lt;/choose&gt;&lt;text&gt; remaining.&lt;/text&gt;&lt;/attemptsRemain_xml&gt;</attemptsRemain_xml><multiAnswerFeedback_xml>&lt;text&gt;You got &lt;/text&gt;&lt;val id="score"/&gt;&lt;text&gt; out of &lt;/text&gt;&lt;val id="total"/&gt;&lt;text&gt; correct.&lt;/text&gt;</multiAnswerFeedback_xml><markedFeedback_xml>&lt;text&gt;You got &lt;/text&gt;&lt;val id="percent"/&gt;&lt;text&gt;% for this marked interaction.&lt;/text&gt;</markedFeedback_xml><showPrefix>true</showPrefix><prefixActivityLevel>false</prefixActivityLevel><prefixStartIndex /><useActiveChoiceMode>true</useActiveChoiceMode><editTextButtonLabel /><leaveTextAsIsButtonLabel /><hideUndoRedoFeature>true</hideUndoRedoFeature><hideResetButton>false</hideResetButton><question_xml><question><start_text>We spend two weeks at a lovely cottage &lt;u&gt;in&lt;/u&gt; the west coast of Ireland every summer.</start_text><correct_text>We spend two weeks at a lovely cottage on the west coast of Ireland every summer.</correct_text><label /><audio_url /><skipPrefix>false</skipPrefix><modelAnswerString>We spend two weeks at a lovely cottage &lt;b&gt;on&lt;/b&gt; the west coast of Ireland every summer.</modelAnswerString></question><question><start_text>Jason has breakfast &lt;u&gt;at&lt;/u&gt; a small café on his way to work every morning.</start_text><correct_text>Jason has breakfast at a small café on his way to work every morning.</correct_text><label /><audio_url /><skipPrefix>false</skipPrefix><modelAnswerString>Jason has breakfast at a small café on his way to work every morning.&lt;br/&gt;
&lt;i&gt;No change was necessary&lt;/i&gt;
</modelAnswerString></question><question><start_text>I'm afraid your name is not &lt;u&gt;on&lt;/u&gt; the list so you can't come in.</start_text><correct_text>I'm afraid your name is not on the list so you can't come in.</correct_text><label /><audio_url /><skipPrefix>false</skipPrefix><modelAnswerString>I'm afraid your name is not on the list so you can't come in.&lt;br/&gt;
&lt;i&gt;No change was necessary&lt;/i&gt;
</modelAnswerString></question><question><start_text>Mike and Jenny left London to live &lt;u&gt;at&lt;/u&gt; a farm in the country.</start_text><label /><audio_url /><skipPrefix>false</skipPrefix><modelAnswerString>Mike and Jenny left London to live &lt;b&gt;on&lt;/b&gt; a farm in the country.</modelAnswerString><correct_text>Mike and Jenny left London to live on a farm in the country.</correct_text></question><question><start_text>My contact details are &lt;u&gt;at&lt;/u&gt; the bottom of every email I send.</start_text><correct_text>My contact details are at the bottom of every email I send.</correct_text><label /><audio_url /><skipPrefix>false</skipPrefix><modelAnswerString>My contact details are at the bottom of every email I send.&lt;br/&gt;
&lt;i&gt;No change was necessary&lt;/i&gt;
</modelAnswerString></question><question><start_text>There were no seats left so we stood &lt;u&gt;in&lt;/u&gt; the back of the hall to hear the lecture.</start_text><correct_text>There were no seats left so we stood at the back of the hall to hear the lecture.</correct_text><label /><audio_url /><skipPrefix>false</skipPrefix><modelAnswerString>There were no seats left so we stood &lt;b&gt;at&lt;/b&gt; the back of the hall to hear the lecture.</modelAnswerString></question><question><start_text>The bathroom is &lt;u&gt;on&lt;/u&gt; the top of the stairs on your right.</start_text><correct_text>The bathroom is at the top of the stairs on your right.</correct_text><label /><audio_url /><skipPrefix>false</skipPrefix><modelAnswerString>The bathroom is &lt;b&gt;at&lt;/b&gt; the top of the stairs on your right.</modelAnswerString></question><question><start_text>Helen explained how she felt &lt;u&gt;in&lt;/u&gt; a letter to Ronald.</start_text><correct_text>Helen explained how she felt in a letter to Ronald.</correct_text><label /><audio_url /><skipPrefix>false</skipPrefix><modelAnswerString>Helen explained how she felt in a letter to Ronald.&lt;br/&gt;
&lt;i&gt;No change was necessary&lt;/i&gt;
</modelAnswerString></question><question><start_text>The police caught the robber because he was &lt;u&gt;on&lt;/u&gt; a photograph taken at the time of the robbery.</start_text><correct_text>The police caught the robber because he was in a photograph taken at the time of the robbery.</correct_text><label /><audio_url /><skipPrefix>false</skipPrefix><modelAnswerString>The police caught the robber because he was &lt;b&gt;in&lt;/b&gt; a photograph taken at the time of the robbery.</modelAnswerString></question><question><start_text>During the airshow there were no clouds &lt;u&gt;in&lt;/u&gt; the sky, so we had a perfect view.</start_text><correct_text>During the airshow there were no clouds in the sky, so we had a perfect view.</correct_text><label /><audio_url /><skipPrefix>false</skipPrefix><modelAnswerString>During the airshow there were no clouds in the sky, so we had a perfect view. &lt;br/&gt;
&lt;i&gt;No change was necessary&lt;/i&gt;</modelAnswerString></question></question_xml><correctFeedback_str /><incorrectFeedback_str /><attemptsAllowed>1</attemptsAllowed></mcq_xml></params_xml><alignment>left</alignment><alignPercent>70</alignPercent><custom_style_name /><sharedTokenBankId /><is_sequential>False</is_sequential><is_compulsory>False</is_compulsory><states><state id="queued" visible="True" enabled="False" /><state id="in_progress" visible="True" enabled="True" /><state id="complete" visible="True" enabled="True" /><state id="checked" visible="True" enabled="True" /><state id="closed" visible="True" enabled="False" /></states></params></object><object linkID="spacer"><params><alignment>right</alignment><alignPercent>30</alignPercent><params_xml><useHeight>false</useHeight><height>100</height></params_xml></params></object><object linkID="background_image"><params><imageURL>learning_objects/assets/1242.png</imageURL><horizontalAlign>left</horizontalAlign><verticalAlign>top</verticalAlign><custom_style_name /><sharedTokenBankId /><is_sequential>False</is_sequential><is_compulsory>False</is_compulsory><states><state id="queued" visible="True" enabled="False" /><state id="in_progress" visible="True" enabled="True" /><state id="complete" visible="True" enabled="True" /><state id="checked" visible="True" enabled="True" /><state id="closed" visible="True" enabled="False" /></states></params></object><object linkID="background_image"><params><imageURL>learning_objects/assets/egurhpbg.png</imageURL><horizontalAlign>center</horizontalAlign><verticalAlign>bottom</verticalAlign><custom_style_name /><sharedTokenBankId /><is_sequential>False</is_sequential><is_compulsory>False</is_compulsory><states><state id="queued" visible="True" enabled="False" /><state id="in_progress" visible="True" enabled="True" /><state id="complete" visible="True" enabled="True" /><state id="checked" visible="True" enabled="True" /><state id="closed" visible="True" enabled="False" /></states></params></object></objects></page>